{
  "page": {
    "page_number": 402,
    "header": "MATHEMATICAL TABLES",
    "blocks": [
      {
        "type": "table",
        "caption": "TABLE IV—Naperian, Natural, or Hyperbolic Logarithms",
        "columns": [
          "Index",
          "0",
          "1",
          "2",
          "3",
          "4",
          "5",
          "6",
          "7",
          "8",
          "9"
        ],
        "rows": [
          [
            "0",
            "1",
            "0.000000",
            "0.693147",
            "1.098612",
            "1.386294",
            "1.609438",
            "1.791759",
            "1.945910",
            "2.302585",
            "2.718282"
          ],
          [
            "1",
            "1",
            "0.000000",
            "0.693147",
            "1.098612",
            "1.386294",
            "1.609438",
            "1.791759",
            "1.945910",
            "2.302585",
            "2.718282"
          ],
          [
            "2",
            "2",
            "0.000000",
            "0.693147",
            "1.098612",
            "1.386294",
            "1.609438",
            "1.791759",
            "1.945910",
            "2.302585",
            "2.718282"
          ],
          [
            "3",
            "3",
            "0.000000",
            "0.693147",
            "1.098612",
            "1.386294",
            "1.609438",
            "1.791759",
            "1.945910",
            "2.302585",
            "2.718282"
          ],
          [
            "4",
            "4",
            "0.000000",
            "0.693147",
            "1.098612",
            "1.386294",
            "1.609438",
            "1.791759",
            "1.945910",
            "2.302585",
            "2.718282"
          ],
          [
            "5",
            "5",
            "0.000000",
            "0.693147",
            "1.098612",
            "1.386294",
            "1.609438",
            "1.791759",
            "1.945910",
            "2.302585",
            "2.718282"
          ],
          [
            "6",
            "6",
            "0.000000",
            "0.693147",
            "1.098612",
            "1.386294",
            "1.609438",
            "1.791759",
            "1.945910",
            "2.302585",
            "2.718282"
          ],
          [
            "7",
            "7",
            "0.000000",
            "0.693147",
            "1.098612",
            "1.386294",
            "1.609438",
            "1.791759",
            "1.945910",
            "2.302585",
            "2.718282"
          ],
          [
            "8",
            "8",
            "0.000000",
            "0.693147",
            "1.098612",
            "1.386294",
            "1.609438",
            "1.791759",
            "1.945910",
            "2.302585",
            "2.718282"
          ],
          [
            "9",
            "9",
            "0.000000",
            "0.693147",
            "1.098612",
            "1.386294",
            "1.609438",
            "1.791759",
            "1.945910",
            "2.302585",
            "2.718282"
          ],
          [
            "Mean Differences",
            " ",
            "[UNRECOGNIZED TEXT]",
            "[UNRECOGNIZED TEXT]",
            "[UNRECOGNIZED TEXT]",
            "[UNRECOGNIZED TEXT]",
            "[UNRECOGNIZED TEXT]",
            "[UNRECOGNIZED TEXT]",
            "[UNRECOGNIZED TEXT]",
            "[UNRECOGNIZED TEXT]",
            "[UNRECOGNIZED TEXT]"
          ]
        ]
      }
    ]
  },
  "cost": 0.0009861
}